vyser/__init__.py
vyser/diagnostics/__init__.py
vyser/diagnostics/diagnostic.py
vyser/diagnostics/diagnostic_bag.py
vyser/diagnostics/text_span.py
vyser/rules/__init__.py
vyser/rules/base.py
vyser/rules/context.py
vyser/rules/engine.py
vyser/rules/factory.py
vyser/syntax/__init__.py
vyser/syntax/binary_expression_syntax.py
vyser/syntax/evaluator.py
vyser/syntax/expression_syntax.py
vyser/syntax/iterator.py
vyser/syntax/lexer.py
vyser/syntax/literal_expression_syntax.py
vyser/syntax/name_expression_syntax.py
vyser/syntax/parenthesis_expression_syntax.py
vyser/syntax/parser.py
vyser/syntax/syntax_facts.py
vyser/syntax/syntax_kind.py
vyser/syntax/syntax_node.py
vyser/syntax/syntax_token.py
vyser/syntax/syntax_tree.py
vyser/syntax/unary_expression_syntax.py
vyser-0.0.2.dist-info/LICENSE
vyser-0.0.2.dist-info/METADATA
vyser-0.0.2.dist-info/WHEEL
vyser-0.0.2.dist-info/top_level.txt
vyser-0.0.2.dist-info/RECORD
